locatepy/locatepy.py
locatepy/data/world-admin-bounds.db
locatepy-1.0.0.dist-info/METADATA
locatepy-1.0.0.dist-info/WHEEL
locatepy-1.0.0.dist-info/top_level.txt
locatepy-1.0.0.dist-info/RECORD
