Metadata-Version: 2.4
Name: locatepy
Version: 1.0.0
Summary: Lightweight reverse geolocation
Author: Samir Sellars
License: MIT
Requires-Python: >=3.9.17
Requires-Dist: shapely
Provides-Extra: dev
Requires-Dist: pytest; extra == "dev"
Requires-Dist: ruff; extra == "dev"
